examples/__init__.py
examples/laygo2_tech/__init__.py
examples/laygo2_tech/laygo2_tech_grids.py
examples/laygo2_tech/laygo2_tech_templates.py
laygo2/__init__.py
laygo2/_typing.py
laygo2/interface/__init__.py
laygo2/interface/bag.py
laygo2/interface/gds.py
laygo2/interface/gds_default.layermap
laygo2/interface/gdspy.py
laygo2/interface/magic.py
laygo2/interface/magic_export.tcl
laygo2/interface/mpl.py
laygo2/interface/mpl_bak.py
laygo2/interface/skill.py
laygo2/interface/skill_export.il
laygo2/interface/skillbridge.py
laygo2/interface/yaml.py
laygo2/object/__init__.py
laygo2/object/database.py
laygo2/object/physical.py
laygo2/object/grid/__init__.py
laygo2/object/grid/core.py
laygo2/object/grid/placement.py
laygo2/object/grid/routing.py
laygo2/object/grid/uniformrouting.py
laygo2/object/technology/__init__.py
laygo2/object/technology/core.py
laygo2/object/technology/nifty.py
laygo2/object/template/__init__.py
laygo2/object/template/core.py
laygo2/object/template/routing.py
laygo2/object/template/tile.py
laygo2/util/__init__.py
laygo2/util/transform.py
laygo2-0.6.9.dist-info/LICENSE
laygo2-0.6.9.dist-info/METADATA
laygo2-0.6.9.dist-info/WHEEL
laygo2-0.6.9.dist-info/top_level.txt
laygo2-0.6.9.dist-info/RECORD
