Metadata-Version: 2.1
Name: laygo2
Version: 0.6.9
Summary: LAYout with Gridded Object 2 - A Python Package for Scripted IC Layout Generation Flow
Home-page: https://github.com/niftylab/laygo2
Author: Jaeduk Han
License: BSD 3-Clause License
Requires-Python: >=3.5
License-File: LICENSE
